cv2/__init__.py
cv2/cv2.so
cv2/libAutoPlugin.so
cv2/libHeteroPlugin.so
cv2/libMKLDNNPlugin.so
cv2/libMultiDevicePlugin.so
cv2/libavcodec.so
cv2/libavformat.so
cv2/libavutil.so
cv2/libformat_reader.so
cv2/libfrontend_manager.so
cv2/libie_backend.so
cv2/libinference_engine.so
cv2/libinference_engine_c_api.so
cv2/libinference_engine_ir_reader.so
cv2/libinference_engine_ir_v7_reader.so
cv2/libinference_engine_legacy.so
cv2/libinference_engine_lp_transformations.so
cv2/libinference_engine_onnx_reader.so
cv2/libinference_engine_preproc.so
cv2/libinference_engine_snippets.so
cv2/libinference_engine_transformations.so
cv2/libinterpreter_backend.so
cv2/libmyriadPlugin.so
cv2/libngraph.so
cv2/libngraph_backend.so
cv2/libonnx_importer.so
cv2/libonnx_proto.so
cv2/libprotobuf.so
cv2/libprotoc.so
cv2/libswscale.so
cv2/libtbb.so.2
cv2/libtemplatePlugin.so
cv2/libtemplate_extension.so
cv2/pcie-ma2x8x.mvcmd
cv2/plugins.xml
cv2/usb-ma2x8x.mvcmd
opencv_python_inference_engine-2022.1.5.dist-info/LICENSE
opencv_python_inference_engine-2022.1.5.dist-info/LICENSE_MIT
opencv_python_inference_engine-2022.1.5.dist-info/METADATA
opencv_python_inference_engine-2022.1.5.dist-info/WHEEL
opencv_python_inference_engine-2022.1.5.dist-info/top_level.txt
opencv_python_inference_engine-2022.1.5.dist-info/RECORD
