Metadata-Version: 2.1
Name: opencv-python-inference-engine
Version: 2022.1.5
Summary: Wrapper package for OpenCV with Inference Engine python bindings
Home-page: https://github.com/banderlog/opencv-python-inference-engine
Maintainer: Kabakov Borys
License: MIT, Apache 2.0
Platform: UNKNOWN
Classifier: Development Status :: 5 - Production/Stable
Classifier: Environment :: Console
Classifier: Intended Audience :: Developers
Classifier: Intended Audience :: Education
Classifier: Intended Audience :: Information Technology
Classifier: Intended Audience :: Science/Research
Classifier: Programming Language :: Python :: 3
Classifier: Programming Language :: C++
Classifier: Operating System :: POSIX :: Linux
Classifier: Topic :: Scientific/Engineering
Classifier: Topic :: Scientific/Engineering :: Image Recognition
Classifier: Topic :: Software Development
License-File: LICENSE
License-File: LICENSE_MIT
Requires-Dist: numpy
